ndvipy/__init__.py
ndvipy/client.py
ndvipy/exceptions.py
ndvipy-0.1.3.dist-info/METADATA
ndvipy-0.1.3.dist-info/WHEEL
ndvipy-0.1.3.dist-info/top_level.txt
ndvipy-0.1.3.dist-info/RECORD
