Metadata-Version: 2.4
Name: ndvipy
Version: 0.1.3
Summary: Python SDK for NDVI Pro cloud service - Generate vegetation analysis from satellite imagery
Author-email: NDVI Pro Team <support@ndvipro.com>
Maintainer-email: NDVI Pro Team <support@ndvipro.com>
License: MIT
Project-URL: Homepage, https://github.com/ndvipro/ndvipy
Project-URL: Documentation, https://github.com/ndvipro/ndvipy#readme
Project-URL: Repository, https://github.com/ndvipro/ndvipy.git
Project-URL: Issues, https://github.com/ndvipro/ndvipy/issues
Keywords: ndvi,satellite,vegetation,remote-sensing,geospatial,agriculture
Classifier: Development Status :: 4 - Beta
Classifier: Intended Audience :: Developers
Classifier: Intended Audience :: Science/Research
Classifier: License :: OSI Approved :: MIT License
Classifier: Operating System :: OS Independent
Classifier: Programming Language :: Python :: 3
Classifier: Programming Language :: Python :: 3.8
Classifier: Programming Language :: Python :: 3.9
Classifier: Programming Language :: Python :: 3.10
Classifier: Programming Language :: Python :: 3.11
Classifier: Programming Language :: Python :: 3.12
Classifier: Topic :: Scientific/Engineering :: GIS
Classifier: Topic :: Software Development :: Libraries :: Python Modules
Requires-Python: >=3.8
Requires-Dist: requests>=2.25.0
Requires-Dist: pillow>=8.0.0
Provides-Extra: dev
Requires-Dist: pytest>=6.0; extra == "dev"
Requires-Dist: pytest-cov; extra == "dev"
Requires-Dist: black; extra == "dev"
Requires-Dist: isort; extra == "dev"
Requires-Dist: flake8; extra == "dev"
